unqlite.cpython-312-darwin.so
medspacy_unqlite-0.9.8.dist-info/RECORD
medspacy_unqlite-0.9.8.dist-info/WHEEL
medspacy_unqlite-0.9.8.dist-info/top_level.txt
medspacy_unqlite-0.9.8.dist-info/METADATA
medspacy_unqlite-0.9.8.dist-info/licenses/LICENSE
medspacy_unqlite-0.9.8.dist-info/licenses/LICENSE_MIT
