Metadata-Version: 2.4
Name: medspacy_unqlite
Version: 0.9.8
Summary: Fast Python bindings for the UnQLite embedded NoSQL database.
Home-page: https://github.com/medspacy/medspacy-unqlite
Author: ['Charles Leifer', 'medspacy']
Author-email: 
License: MIT AND the license inherit from Charles Leifer
Project-URL: Release notes, https://github.com/medspacy/unqlite-python/releases
Project-URL: Source, https://github.com/medspacy/unqlite-python
Classifier: Development Status :: 5 - Production/Stable
Classifier: Environment :: Console
Classifier: Intended Audience :: Developers
Classifier: Intended Audience :: Science/Research
Classifier: License :: OSI Approved :: MIT License
Classifier: Operating System :: POSIX :: Linux
Classifier: Operating System :: MacOS :: MacOS X
Classifier: Operating System :: Microsoft :: Windows
Classifier: Programming Language :: Cython
Classifier: Programming Language :: Python :: 3
Classifier: Programming Language :: Python :: 3.8
Classifier: Programming Language :: Python :: 3.9
Classifier: Programming Language :: Python :: 3.10
Classifier: Programming Language :: Python :: 3.11
Classifier: Topic :: Scientific/Engineering
License-File: LICENSE
License-File: LICENSE_MIT
Dynamic: author
Dynamic: home-page
Dynamic: license-file
Dynamic: summary
